bert_sample
