Metadata-Version: 1.0
Name: bert-sample
Version: 0.0.0.2
Summary: bert
Home-page: https://www.terrychan.org
Author: Terry Chan
Author-email: napoler2008@gmail.com
License: UNKNOWN
Platform: UNKNOWN
